{
  "Scm": {
    "Type": "PlasticScm",
    "ChangeId": "95318",
    "Branch": "main",
    "Repo": "rust_reboot",
    "Comment": "GetNextPathPosition NRE fix",
    "Author": "adam",
    "Date": "02/04/2024 15:35:35",
    "Items": "C Assets\\Rust.Ai\\BaseNavigator.cs"
  },
  "Build": {
    "Id": "5775",
    "Number": "5775",
    "Tag": "jenkins-RustServer-5775",
    "Url": "https://build.facepunch.com/job/RustServer/5775/",
    "Name": "RustServer",
    "Node": "Win4"
  },
  "Date": 1712070872,
  "DateString": "2 04 2024",
  "TimeString": "15:14"
}